unfair_data_generator/__init__.py
unfair_data_generator/unfair_classification.py
unfair_data_generator/util/helpers.py
unfair_data_generator/util/model_trainer.py
unfair_data_generator/util/visualizer.py
unfair_data_generator-0.1.0.dist-info/LICENSE
unfair_data_generator-0.1.0.dist-info/METADATA
unfair_data_generator-0.1.0.dist-info/WHEEL
unfair_data_generator-0.1.0.dist-info/RECORD
