Metadata-Version: 2.1
Name: unfair-data-generator
Version: 0.1.0
Summary: 
Author: Sašo Karakatič
Author-email: karakatic@gmail.com
Requires-Python: >=3.11,<4.0
Classifier: Programming Language :: Python :: 3
Classifier: Programming Language :: Python :: 3.11
Classifier: Programming Language :: Python :: 3.12
Provides-Extra: docs
Requires-Dist: matplotlib (>=3.7.5,<3.8.0)
Requires-Dist: numpy (>=1.26.0,<2.0.0)
Requires-Dist: pandas (>=2.3.1,<3.0.0)
Requires-Dist: scikit-learn (>=1.3.2,<1.4.0)
Requires-Dist: sphinx-rtd-theme[docs] (>=1.0.0,<2.0.0) ; extra == "docs"
Requires-Dist: sphinx[docs] (>=5.0,<6.0) ; extra == "docs"
